MANIFEST.in
README.md
setup.cfg
setup.py
drf-authtoken/__init__.py
drf-authtoken/settings.py
drf-authtoken/urls.py
drf-authtoken/wsgi.py
drf_auth/__init__.py
drf_auth/apps.py
drf_auth/mail.py
drf_auth/serializers.py
drf_auth/tests.py
drf_auth/urls.py
drf_auth/views.py
drf_auth/migrations/__init__.py
drf_restauth.egg-info/PKG-INFO
drf_restauth.egg-info/SOURCES.txt
drf_restauth.egg-info/dependency_links.txt
drf_restauth.egg-info/requires.txt
drf_restauth.egg-info/top_level.txt